{
  "timestamp": "2026-03-31T23:40:01.625753",
  "crypto": {
    "bitcoin": {
      "name": "Bitcoin",
      "symbol": "BTC",
      "price": 67026,
      "change_24h": -1.00678,
      "market_cap": 1340071275712,
      "volume": 51597780225,
      "high_24h": 68130,
      "low_24h": 66038
    },
    "ethereum": {
      "name": "Ethereum",
      "symbol": "ETH",
      "price": 2061.43,
      "change_24h": -0.61008,
      "market_cap": 248690353799,
      "volume": 17733495515,
      "high_24h": 2085.71,
      "low_24h": 2014.13
    },
    "ripple": {
      "name": "XRP",
      "symbol": "XRP",
      "price": 1.32,
      "change_24h": -1.61002,
      "market_cap": 81075798441,
      "volume": 2050704109,
      "high_24h": 1.35,
      "low_24h": 1.31
    },
    "solana": {
      "name": "Solana",
      "symbol": "SOL",
      "price": 81.09,
      "change_24h": -3.67955,
      "market_cap": 46440322421,
      "volume": 4071332094,
      "high_24h": 84.6,
      "low_24h": 80.39
    },
    "cardano": {
      "name": "Cardano",
      "symbol": "ADA",
      "price": 0.239643,
      "change_24h": -3.60641,
      "market_cap": 8834151194,
      "volume": 376436570,
      "high_24h": 0.249282,
      "low_24h": 0.239621
    }
  },
  "stocks": {
    "NASDAQ": {
      "name": "納斯達克指數",
      "symbol": "^IXIC",
      "price": 21185.082,
      "change": 0,
      "volume": 4141434000,
      "high": 21257.043,
      "low": 21063.379
    },
    "DJI": {
      "name": "道瓊斯指數",
      "symbol": "^DJI",
      "price": 45712.03,
      "change": 0,
      "volume": 174614877,
      "high": 45892.21,
      "low": 45480.3
    },
    "SP500": {
      "name": "標普500指數",
      "symbol": "^GSPC",
      "price": 6433.44,
      "change": 0,
      "volume": 961104845,
      "high": 6453.73,
      "low": 6395.88
    },
    "AAPL": {
      "name": "蘋果公司",
      "symbol": "AAPL",
      "price": 248.505,
      "change": 0,
      "volume": 9876773,
      "high": 249.27,
      "low": 247.101
    },
    "TSLA": {
      "name": "特斯拉",
      "symbol": "TSLA",
      "price": 364.322,
      "change": 0,
      "volume": 27165216,
      "high": 366.1,
      "low": 361.24
    }
  },
  "commodities": {
    "gold": {
      "name": "黃金",
      "symbol": "GC=F",
      "price": 4639.5,
      "change": 0,
      "unit": "USD/oz"
    },
    "silver": {
      "name": "白銀",
      "symbol": "SI=F",
      "price": 73.77,
      "change": 0,
      "unit": "USD/oz"
    },
    "oil_wti": {
      "name": "WTI原油",
      "symbol": "CL=F",
      "price": 104.52,
      "change": 0,
      "unit": "USD/barrel"
    },
    "oil_brent": {
      "name": "布倫特原油",
      "symbol": "BZ=F",
      "price": 107.56,
      "change": 0,
      "unit": "USD/barrel"
    }
  },
  "forex": {
    "USDHKD": {
      "name": "美元/港幣",
      "from_currency": "USD",
      "to_currency": "HKD",
      "rate": 7.84,
      "change": 0
    },
    "USDCNY": {
      "name": "美元/人民幣",
      "from_currency": "USD",
      "to_currency": "CNY",
      "rate": 6.8975,
      "change": 0
    },
    "EURUSD": {
      "name": "歐元/美元",
      "from_currency": "EUR",
      "to_currency": "USD",
      "rate": 1.1523,
      "change": 0
    },
    "GBPUSD": {
      "name": "英鎊/美元",
      "from_currency": "GBP",
      "to_currency": "USD",
      "rate": 1.3203,
      "change": 0
    },
    "USDJPY": {
      "name": "美元/日元",
      "from_currency": "USD",
      "to_currency": "JPY",
      "rate": 159.029,
      "change": 0
    }
  },
  "bonds": {
    "us10y": {
      "name": "美國10年期國債",
      "country": "US",
      "maturity": "10Y",
      "yield": 4.322,
      "change": 0
    },
    "us2y": {
      "name": "美國2年期國債",
      "country": "US",
      "maturity": "2Y",
      "yield": 4.322,
      "change": 0
    },
    "us30y": {
      "name": "美國30年期國債",
      "country": "US",
      "maturity": "30Y",
      "yield": 4.91,
      "change": 0
    }
  },
  "market_sentiment": {
    "fear_greed_index": 31,
    "sentiment": "恐懼",
    "description": "市場情緒悲觀，投資者信心不足",
    "color": "#66CCFF",
    "timestamp": "2026-03-31T23:40:03.781800"
  }
}