{
  "timestamp": "2026-04-04T11:00:03.918012",
  "total_news": 10,
  "news": [
    {
      "title": "Warren Buffett says he's still making calls on investments at Berkshire, flags 'tiny' new buy",
      "link": "https://www.cnbc.com/2026/03/31/warren-buffett-says-hes-still-making-calls-on-investments-at-berkshire-flags-tiny-new-buy.html",
      "summary": "The 95-year-old investor said he still comes into the office daily and stays engaged with markets.",
      "source": "CNBC",
      "category": "business",
      "timestamp": "2026-04-04T11:00:03.459641"
    },
    {
      "title": "Warren Buffett says he sold Apple too soon and would buy more of it, though not in this market",
      "link": "https://www.cnbc.com/2026/03/31/warren-buffett-says-he-sold-apple-too-soon-and-would-buy-more-of-it-though-not-in-this-market-.html",
      "summary": "Apple remains Berkshire Hathaway's largest holding even after the conglomerate trimmed its stake at the end of last year.",
      "source": "CNBC",
      "category": "business",
      "timestamp": "2026-04-04T11:00:03.459615"
    },
    {
      "title": "Warren Buffett says Iran bomb would make nuclear disaster harder to avoid",
      "link": "https://www.cnbc.com/2026/03/31/warren-buffett-says-iran-bomb-would-make-nuclear-disaster-harder-to-avoid.html",
      "summary": "The Berkshire Hathaway chairman said the growing number of nuclear-armed states has fundamentally altered the global risk landscape.",
      "source": "CNBC",
      "category": "business",
      "timestamp": "2026-04-04T11:00:03.459586"
    },
    {
      "title": "Visa launches new AI tools to manage the charge dispute process",
      "link": "https://www.cnbc.com/2026/04/01/visa-ai-tools-dispute-management.html",
      "summary": "Visa's new tools are part of a larger push by major banks and financial institutions to incorporate AI into their businesses.",
      "source": "CNBC",
      "category": "business",
      "timestamp": "2026-04-04T11:00:03.459556"
    },
    {
      "title": "Blue Owl caps private credit funds redemptions at 5% after steep request levels",
      "link": "https://www.cnbc.com/2026/04/02/blue-owl-private-credit-funds-redemptions-requests.html",
      "summary": "Blue Owl attributed the higher-than-usual requests to \"heightened market concerns around AI-related disruption to software companies.\"",
      "source": "CNBC",
      "category": "business",
      "timestamp": "2026-04-04T11:00:03.459495"
    },
    {
      "title": "Here's what 'cracking' bitcoin in 9 minutes by quantum computers actually means",
      "link": "https://www.coindesk.com/tech/2026/03/31/what-does-cracking-bitcoin-in-9-minutes-by-quantum-computers-actually-mean",
      "summary": "",
      "source": "CoinDesk",
      "category": "crypto",
      "timestamp": "2026-04-04T02:30:00+00:00"
    },
    {
      "title": "Schwab plans spot bitcoin, ether trading launch in first half of 2026",
      "link": "https://www.coindesk.com/business/2026/04/03/schwab-plans-spot-bitcoin-ether-trading-launch-in-first-half-of-2026",
      "summary": "",
      "source": "CoinDesk",
      "category": "crypto",
      "timestamp": "2026-04-03T19:18:00+00:00"
    },
    {
      "title": "Circle under fire after $285 million Drift hack over inaction to freeze stolen USDC",
      "link": "https://www.coindesk.com/business/2026/04/03/circle-under-fire-after-usd285-million-drift-hack-over-inaction-to-freeze-stolen-usdc",
      "summary": "",
      "source": "CoinDesk",
      "category": "crypto",
      "timestamp": "2026-04-03T19:02:51+00:00"
    },
    {
      "title": "What next as XRP rises to $1.33 but fails to break out",
      "link": "https://www.coindesk.com/markets/2026/04/03/what-next-as-xrp-rises-to-usd1-33-but-fails-to-break-out",
      "summary": "",
      "source": "CoinDesk",
      "category": "crypto",
      "timestamp": "2026-04-03T16:32:33+00:00"
    },
    {
      "title": "CoinDesk 20 performance update: Bitcoin (BTC) trades flat while altcoins rise",
      "link": "https://www.coindesk.com/coindesk-indices/2026/04/03/coindesk-20-performance-update-bitcoin-btc-trades-flat-while-altcoins-rise",
      "summary": "",
      "source": "CoinDesk",
      "category": "crypto",
      "timestamp": "2026-04-03T13:18:50+00:00"
    }
  ],
  "categories": {
    "crypto": [
      {
        "title": "Here's what 'cracking' bitcoin in 9 minutes by quantum computers actually means",
        "link": "https://www.coindesk.com/tech/2026/03/31/what-does-cracking-bitcoin-in-9-minutes-by-quantum-computers-actually-mean",
        "summary": "",
        "source": "CoinDesk",
        "category": "crypto",
        "timestamp": "2026-04-04T02:30:00+00:00"
      },
      {
        "title": "Schwab plans spot bitcoin, ether trading launch in first half of 2026",
        "link": "https://www.coindesk.com/business/2026/04/03/schwab-plans-spot-bitcoin-ether-trading-launch-in-first-half-of-2026",
        "summary": "",
        "source": "CoinDesk",
        "category": "crypto",
        "timestamp": "2026-04-03T19:18:00+00:00"
      },
      {
        "title": "Circle under fire after $285 million Drift hack over inaction to freeze stolen USDC",
        "link": "https://www.coindesk.com/business/2026/04/03/circle-under-fire-after-usd285-million-drift-hack-over-inaction-to-freeze-stolen-usdc",
        "summary": "",
        "source": "CoinDesk",
        "category": "crypto",
        "timestamp": "2026-04-03T19:02:51+00:00"
      },
      {
        "title": "What next as XRP rises to $1.33 but fails to break out",
        "link": "https://www.coindesk.com/markets/2026/04/03/what-next-as-xrp-rises-to-usd1-33-but-fails-to-break-out",
        "summary": "",
        "source": "CoinDesk",
        "category": "crypto",
        "timestamp": "2026-04-03T16:32:33+00:00"
      },
      {
        "title": "CoinDesk 20 performance update: Bitcoin (BTC) trades flat while altcoins rise",
        "link": "https://www.coindesk.com/coindesk-indices/2026/04/03/coindesk-20-performance-update-bitcoin-btc-trades-flat-while-altcoins-rise",
        "summary": "",
        "source": "CoinDesk",
        "category": "crypto",
        "timestamp": "2026-04-03T13:18:50+00:00"
      }
    ],
    "stocks": [],
    "economy": [],
    "technology": [],
    "other": [
      {
        "title": "Warren Buffett says he's still making calls on investments at Berkshire, flags 'tiny' new buy",
        "link": "https://www.cnbc.com/2026/03/31/warren-buffett-says-hes-still-making-calls-on-investments-at-berkshire-flags-tiny-new-buy.html",
        "summary": "The 95-year-old investor said he still comes into the office daily and stays engaged with markets.",
        "source": "CNBC",
        "category": "business",
        "timestamp": "2026-04-04T11:00:03.459641"
      },
      {
        "title": "Warren Buffett says he sold Apple too soon and would buy more of it, though not in this market",
        "link": "https://www.cnbc.com/2026/03/31/warren-buffett-says-he-sold-apple-too-soon-and-would-buy-more-of-it-though-not-in-this-market-.html",
        "summary": "Apple remains Berkshire Hathaway's largest holding even after the conglomerate trimmed its stake at the end of last year.",
        "source": "CNBC",
        "category": "business",
        "timestamp": "2026-04-04T11:00:03.459615"
      },
      {
        "title": "Warren Buffett says Iran bomb would make nuclear disaster harder to avoid",
        "link": "https://www.cnbc.com/2026/03/31/warren-buffett-says-iran-bomb-would-make-nuclear-disaster-harder-to-avoid.html",
        "summary": "The Berkshire Hathaway chairman said the growing number of nuclear-armed states has fundamentally altered the global risk landscape.",
        "source": "CNBC",
        "category": "business",
        "timestamp": "2026-04-04T11:00:03.459586"
      },
      {
        "title": "Visa launches new AI tools to manage the charge dispute process",
        "link": "https://www.cnbc.com/2026/04/01/visa-ai-tools-dispute-management.html",
        "summary": "Visa's new tools are part of a larger push by major banks and financial institutions to incorporate AI into their businesses.",
        "source": "CNBC",
        "category": "business",
        "timestamp": "2026-04-04T11:00:03.459556"
      },
      {
        "title": "Blue Owl caps private credit funds redemptions at 5% after steep request levels",
        "link": "https://www.cnbc.com/2026/04/02/blue-owl-private-credit-funds-redemptions-requests.html",
        "summary": "Blue Owl attributed the higher-than-usual requests to \"heightened market concerns around AI-related disruption to software companies.\"",
        "source": "CNBC",
        "category": "business",
        "timestamp": "2026-04-04T11:00:03.459495"
      }
    ]
  }
}